{
  "id": 92,
  "added": "2010-12-27 20:50:31",
  "modified": "2010-12-31 03:40:41",
  "public": true,
  "metadata": {
    "Creator": [
      "Ola Holm",
      "Siri Lawson, trans."
    ],
    "Date": [
      "1945.08.13"
    ],
    "Language": [
      "Norwegian"
    ],
    "Text": [
      "<p>Tr.heim 13-8-45</p></p>\n<p>Kj&aelig;re broder</p></p>\n<p>Tusind tak for det intresante brev, jeg fik ig&aring;r.<span>&nbsp; </span>Du er sandelig gutten i r&oslash;iken enda.<span>&nbsp; </span>Det er virkelig hyggelig og se at du og fruen er s&aring; rask og r&oslash;rig enda.<span>&nbsp; </span>Her er deilig og varm sommer nu, og Tyskerne som tramper og g&aring;r herifra svetter ogs&aring; s&aelig;rlig de feite officerer som har gj&oslash;dd sig op, ja good=bye med dem, h&aring;per vi er helt fri alle innen oktober m&aring;ned, foresten de andre Soldater ogs&aring;, s&aring; vi for bli for os sj&oslash;l igjen.<span>&nbsp; </span>Du kan tro jeg er intresert i og f&aring; pakker, mange her f&aring;r pakker derfra nu, fra sine sl&aelig;gt og venner og det tr&aelig;nges men hvordan skal vi kunne f&aring; betale det, h&aring;per at ogs&aring; vores penger for sin v&aelig;rdi snart igjen ogs&aring;, men da blir det mindre av dem.<span>&nbsp; </span>Vi har ingen pakker f&aring;et enda men det tar sin tid de som sendes med Baater ser du, vi for nok alt som blir sent, v&aelig;r ikke r&aelig;dd for det.<span>&nbsp; </span>Jeg n&aelig;vnte til kona mi at du skulle sende henne noget, s&aring; du kan tro hun er spent.<span>&nbsp; </span>Hun er lit sliten og tr&aelig;t, men arbeider, og passer sine saker enda.<span>&nbsp; </span>Jeg h&aring;per Alma og du har f&aring;et mine brev og hvor jeg skrev om vores s&oslash;sken, dem har det rigtig bra, Hanna i Narvik, Laura p&aring; Stj&oslash;rdalen, og Axel har det rigtig bra mangler vist ingen ting.<span>&nbsp; </span>Han har nu solgt Bakeriet til sin elste s&oslash;n, s&aring; nu kan han (Axel) ta det med ro.<span>&nbsp; </span>Hans kone er syk og blir nok ikke bra mere.<span>&nbsp; </span>H&aring;per du ikke blev forn&aelig;rmet over alt jeg n&aelig;vnte som vi tr&aelig;nger, s&aring; du m&aring; ikke tro at jeg vil v&aelig;re patr&aelig;ngende heller, men vi har jo ikke hat anledning til og f&aring; kj&oslash;pe s&aring;pas som en t&oslash;y bit eller sko eller undert&oslash;y plagg, hverken for Mand eller kvinne.<span>&nbsp; </span>Silkestr&oslash;mper for Middelstore damer, er det frygtelig sp&oslash;rgsm&aring;l, samt Silke blusset&oslash;yer, for damer.<span>&nbsp; </span>H&aring;per det m&aring; bli noget og f&aring; kj&oslash;pe her ogs&aring; igjen.<span>&nbsp; </span>Ser at krigen snart er slut med &ldquo;Japan&rdquo;, og da blir det vel bedre med v&aelig;rt, men det tar lang tid til vi f&aring;r kl&aelig;der og sko.<span>&nbsp; </span>Sp&oslash;r Alma om hun kan sende mig en &ldquo;Dame Journal&rdquo; &ldquo;Mote Blad for Damer&rdquo;.<span>&nbsp; </span>Du kan skj&oslash;nne jeg kommer til og skrive strax jeg f&aring;r nogen pakker fra dig.<span>&nbsp; </span>Jeg forst&aring;r at dere er spent p&aring; og se om vi for dem.<span>&nbsp; </span>Axel fikk kort (card) fra dig, samtidig som jeg.<span>&nbsp; </span>Jeg har hilset alle vores Sl&aelig;gt her fra dere og forteller at du er &ldquo;still going just as strong as ever&rdquo;, and that you are the same &ldquo;infant terrible&rdquo;.<span>&nbsp; </span>Ja alt er bra, og vi skylder og takke Gud for det gode vi har.<span>&nbsp; </span>Husker ikke mere denne gang, skal snart skrive igjen.<span>&nbsp; </span>Ha det s&aring; inderlig bra da.<span>&nbsp; </span>Hils alle og tak p&aring; forh&aring;nd, for at du er s&aring; snill.</p></p>\n<p>Din Olav</p></p>\n<p>Nonnegt. 4, Trondheim</p></p>\n<p>Hils Alma og alle hennes fra mig</p></p>"
    ],
    "Title": [
      "Ola Holm to John Holm 1945.8.13"
    ],
    "Description": [
      "BREV FRA OLA HOLM DATERT 13. AUGUST-1945, POSTSTEMPLET SAMME DAG, TIL MR. JOHN HOLM, 108 W. 5. ST., DELL RAPIDS, SO. DAK., U.S.A. ÅPNET AV KONTROLLØR 866.  SENDT MED LUFTPOST, FRIMERKENE ER KLIPPET UT."
    ]
  },
  "tags": [
    "1940s",
    "Germans",
    "God",
    "John Holm",
    "Narvik",
    "Norway to US",
    "Ola Holm",
    "POWs",
    "Stjørdal",
    "Trondheim",
    "bakery",
    "censorship",
    "clothes",
    "gifts",
    "magazines",
    "postwar",
    "shoes",
    "silk stockings",
    "underwear"
  ],
  "files": [
    {
      "original": "Ola Holm 13 august-1945.pdf",
      "filename": "9f92377ccb650e3f56efc58672a8397b.pdf",
      "mime_type": "application/pdf"
    }
  ]
}