{
  "id": 102,
  "added": "2010-12-27 22:32:53",
  "modified": "2010-12-27 22:32:53",
  "public": true,
  "metadata": {
    "Title": [
      "Axel Holm to Alma C. Wilson 1945.10.25"
    ],
    "Description": [
      "BREV FRA AXEL HOLM DATERT 25. OKTOBER-1945 TIL FRU ALMA WILSON, 102 W 5 STREET, DELL RAPIDS, S. DAKOTA, U.S.A.  SENDT MED LUFTPOST, FRIMERKENE ER KLIPPET VEKK.   KONVOLUTT FRA –AX. HOLM, STJØRDAL – ALLE SORTER GODT BRØD TIL HVERDAG OG FEST–. SIRKULÆRT –POSTOBLAT-MERKE– PÅ BAKSIDEN, MED POSTHORN OG KRONE."
    ],
    "Creator": [
      "Axel Holm",
      "Siri Lawson, trans."
    ],
    "Date": [
      "1945.10.25"
    ],
    "Language": [
      "Norwegian"
    ],
    "Text": [
      "<p>Stj&oslash;rdal 25-10-45</p></p>\n<p>Kj&aelig;re Alma og dere alle i hopa.</p></p>\n<p>Tak for brevet jeg fik 23 denes.<span>&nbsp; </span>Tak og for di to pakkene jeg fik nu netop<span>&nbsp; </span>Tusin tak for alt<span>&nbsp; </span>Vi har nu foet 4 pakker fra Dere.<span>&nbsp; </span>Du siger at jeg m&aring; si fra vad jeg &oslash;nsker men vi m&aring; pr&oslash;ve og greie os selv s&aring; di slipper alt dette strev for os, det var fint med et par sko<span>&nbsp; </span>jeg bruker nr 44 norsk m&aring;l<span>&nbsp; </span>de sko jeg fik fra Johan var fin men for sm&aring; men dem skal blir benyttet av di som trenger dem.</p></p>\n<p>Min kone ligger fremdeles p&aring; Hegra pleiehjem med 38 i feber.<span>&nbsp; </span>Jeg har nu snart kj&oslash;rt 250 mil og bes&oslash;kt hende s&aring; du forst&aring;r at den Norske kjerlighed er sterk og varm<span>&nbsp; </span>den trodser b&aring;de regn og varm, kulde og storm.<span>&nbsp; </span>Vi har nu lite Tyskere her og snart s&aring; drager Engelsmennerne og s&aring; er vi fri alt dette milit&aelig;re forel&oslash;big<span>&nbsp; </span>her er nu stille<span>&nbsp; </span>det er en periode med lite arbeide og ingen arbeids gl&aelig;de, for det vi for av vor myndigheder er nye skatter og avgifter.</p></p>\n<p>S&aring; for di lev vel alle og ver hilset fra os alle.<span>&nbsp; </span>Skal hilse fra Laura<span>&nbsp; </span>hun sidder nu her p&aring; stuen og strikker.<span>&nbsp; </span>Mindor har veret i Oslo nu. med Ola er de bra<span>&nbsp; </span>Olava likes&aring;.<span>&nbsp; </span>Hun venter nu Odd hjem til jul <em>(han kunne ikke komme hjem f&oslash;r v&aring;ren 1946)</em>.<span>&nbsp; </span>Her er et fint veir<span>&nbsp; </span>jeg arbeider ute hele eftermiddagen.</p></p>\n<p>14 November blir jeg 60 &aring;r lils bane hendes mor, du m&aring; tag med dig Johan og kom s&aring; skal di f&aring; F&aring;r i K&aring;l.</p></p>\n<p>Einar vor yngste s&oslash;n er i milit&aelig;re<span>&nbsp; </span>er nu sykepermiteret<span>&nbsp; </span>han skal til Oslo og bli oppereret for et maveonde.</p></p>\n<p>Helga<span>&nbsp; </span>Axel</p>\r\n<span style=–font-size: 12pt; font-family: Times;–><br /></span></p>\n<p>Stj&oslash;rdal 25-10-45</p></p>\n<p>Dear Alma and you all.</p></p>"
    ]
  },
  "tags": [
    "1940s",
    "Alma C. Wilson",
    "Axel Holm",
    "Britain",
    "Får i Kål",
    "Germans",
    "Hegra",
    "John Holm",
    "Norway to US",
    "POWs",
    "Stjørdal",
    "fever",
    "gifts",
    "knitting",
    "military",
    "nursing home",
    "postwar",
    "request",
    "shoes",
    "sickness"
  ],
  "files": [
    {
      "original": "Axel Holm 25 oktober-1945.pdf",
      "filename": "d9b058c03d99943429d9d652a4412dbf.pdf",
      "mime_type": "application/pdf"
    }
  ]
}