{
  "id": 135,
  "added": "2010-12-28 19:39:39",
  "modified": "2010-12-30 03:49:27",
  "public": true,
  "metadata": {
    "Title": [
      "Gusta Eidum to John Holm 1946.9.5"
    ],
    "Description": [
      "BREV FRA GUSTA EIDUM DATERT 5. SEPTEMBER-1946, TIL HR. JOHN HOLM, 108 WEST 5 ST., DELL RAPIDS, S. DAK., U.S.A.   FRIMERKENE ER KLIPPET VEKK.  SENDT MED LUFTPOST."
    ],
    "Creator": [
      "Gusta Eidum",
      "Siri Lawson, trans."
    ],
    "Date": [
      "1946.09.05"
    ],
    "Language": [
      "Norwegian"
    ],
    "Text": [
      "<p>Narvik 5-9-46</p></p>\n<p>Kj&aelig;re snille onkel!</p></p>\n<p>Takk for brevet far fik dag.<span>&nbsp; </span>Jeg skulle ha skrevet lenge f&oslash;r, men tiden blir bestandig forkort.<span>&nbsp; </span>Tenker s&aring; ofte p&aring; dig<span>&nbsp; </span>skulle &oslash;nske jeg engang fik bes&oslash;ke dig, men det er nok i det uvisse.<span>&nbsp; </span>Men lyst har jeg.<span>&nbsp; </span>Kj&aelig;re onkel<span>&nbsp; </span>nu vil vi at du skal si os hvad det er som er sv&aelig;rt ondt for dere &aring; f&aring; tak i, kanske vi kunne f&aring; den glede &aring; senne dere en pakke ogs&aring;.<span>&nbsp; </span>Kl&aelig;r er det v&aelig;rste og f&aring; tak i her, det er s&aring; vanskelig med alt i t&oslash;i.<span>&nbsp; </span>Mat har vi nok, men mindre med kl&aelig;r.<span>&nbsp; </span>Si os onkel hvad det er lite av der, kanske vi kunne senne dere en liten p&aring;skj&oslash;nnelse f&aring;r alt det som vi har f&aring;tt av dere.<span>&nbsp; </span>Hils Alma fra mig og si jeg skal snart skrive til henne.<span>&nbsp; </span>Jeg strever hele dagen, m&aring; stelle hjemme for mor og far, s&aring; hjelper jeg min svigerinne med s&oslash;nn, det g&aring;r i ett hele dagen.<span>&nbsp; </span>Jeg har idag hv&aelig;rt ute og sett om jeg fant en liten ting fra Norge og senne dere, og det skal snart komme.<span>&nbsp; </span>Mor og far hilser.<span>&nbsp; </span>Mor har det ganske bra efter det at hun brak begge bena sine.<span>&nbsp; </span>Jeg senner et foto av mig slik som jeg ser ut idag.<span>&nbsp; </span>De andre billederne er en skitur vi var p&aring; fjellet.<span>&nbsp; </span>Det er min s&oslash;ster Karen og hennes mand, og min Svigerinne som er gift med min bror Sverre.<span>&nbsp; </span>Kj&aelig;re onkel nu m&aring; du senne mig et brev n&aring;r du f&aring;r tid.<span>&nbsp; </span>Lev vel kj&aelig;re onkel.</p></p>\n<p>&nbsp;</p></p>\n<p>Beste hilsen</p></p>\n<p>Gusta</p></p>\n<p>&nbsp;</p></p>\n<p>&nbsp;</p></p>\n<p>Narvik 5-9-46</p></p>\n<p>Dear kind uncle!</p></p>"
    ]
  },
  "tags": [
    "1940s",
    "Gusta Eidum",
    "John Holm",
    "Narvik",
    "Norway to US",
    "clothes",
    "gifts",
    "postwar"
  ],
  "files": [
    {
      "original": "Gusta Eidum 5 septembr-1946.pdf",
      "filename": "42733562bd96a11db230070ffcc47dbc.pdf",
      "mime_type": "application/pdf"
    }
  ]
}